Workbook

Sheet Raw Data
A1: Order ID | B1: Date | C1: Product | D1: Category | E1: Region | F1: Salesperson | G1: Quantity | H1: Unit Price (₦) | I1: Discount | J1: Revenue (₦) | K1: Cost (₦) | L1: Profit (₦) | M1: Profit Margin
A2: 1 | B2: 46125 | C2: Keyboard | D2: Electronics | E2: Abuja | F2: Grace | G2: 8 | H2: 28500 | I2: 0 | J2: 228000 | K2: 164160 | L2: 63840 | M2: =L2/J2
A3: 2 | B3: 46172 | C3: Headset | D3: Electronics | E3: Kano | F3: David | G3: 8 | H3: 42750 | I3: 0.1 | J3: 307800 | K3: 246240 | L3: 61560 | M3: =L3/J3
A4: 3 | B4: 46183 | C4: Keyboard | D4: Electronics | E4: Port Harcourt | F4: David | G4: 6 | H4: 30000 | I4: 0 | J4: 180000 | K4: 129600 | L4: 50400 | M4: =L4/J4
A5: 4 | B5: 46081 | C5: Printer | D5: Electronics | E5: Abuja | F5: Michael | G5: 9 | H5: 114000 | I5: 0.1 | J5: 923400 | K5: 738720 | L5: 184680 | M5: =L5/J5
A6: 5 | B6: 46153 | C6: Keyboard | D6: Electronics | E6: Kano | F6: Grace | G6: 3 | H6: 31500 | I6: 0 | J6: 94500 | K6: 68040 | L6: 26460 | M6: =L6/J6
A7: 6 | B7: 46154 | C7: Monitor | D7: Electronics | E7: Lagos | F7: Michael | G7: 9 | H7: 168000 | I7: 0.05 | J7: 1436400 | K7: 1088640 | L7: 347760 | M7: =L7/J7
A8: 7 | B8: 46112 | C8: Printer | D8: Electronics | E8: Kano | F8: David | G8: 2 | H8: 120000 | I8: 0 | J8: 240000 | K8: 172800 | L8: 67200 | M8: =L8/J8
A9: 8 | B9: 46057 | C9: Keyboard | D9: Electronics | E9: Lagos | F9: Michael | G9: 7 | H9: 28500 | I9: 0.1 | J9: 179550 | K9: 143640 | L9: 35910 | M9: =L9/J9
A10: 9 | B10: 46156 | C10: Office Chair | D10: Furniture | E10: Abuja | F10: Michael | G10: 8 | H10: 180000 | I10: 0.05 | J10: 1368000 | K10: 1036800 | L10: 331200 | M10: =L10/J10
A11: 10 | B11: 46036 | C11: Printer | D11: Electronics | E11: Port Harcourt | F11: Aisha | G11: 2 | H11: 120000 | I11: 0.05 | J11: 228000 | K11: 172800 | L11: 55200 | M11: =L11/J11
A12: 11 | B12: 46104 | C12: Printer | D12: Electronics | E12: Kano | F12: David | G12: 8 | H12: 114000 | I12: 0 | J12: 912000 | K12: 656640 | L12: 255360 | M12: =L12/J12
A13: 12 | B13: 46067 | C13: Laptop | D13: Electronics | E13: Lagos | F13: Aisha | G13: 9 | H13: 427500 | I13: 0.1 | J13: 3462750 | K13: 2770200 | L13: 692550 | M13: =L13/J13
... A121: 120 | B121: 46176 | C121: Printer | D121: Electronics | E121: Ibadan | F121: Grace | G121: 8 | H121: 120000 | I121: 0 | J121: 960000 | K121: 691200 | L121: 268800 | M121: =L121/J121

Sheet Project Guide
A1: Step | B1: Task | C1: Skills
A2: 1 | B2: Check for duplicates, blanks and incorrect values. | C2: Data cleaning
A3: 2 | B3: Add a Profit Margin column: Profit ÷ Revenue. | C3: Formulas
A4: 3 | B4: Calculate total Revenue, total Profit and total Quantity Sold. | C4: KPI calculations
A5: 4 | B5: Find the best-selling Product by Quantity Sold. | C5: Sorting and filtering
A6: 5 | B6: Find the highest-revenue Region. | C6: Regional analysis
A7: 6 | B7: Find the Salesperson with the highest Profit. | C7: Sales analysis
A8: 7 | B8: Create PivotTables for Revenue by Region and by Product. | C8: PivotTables
A9: 8 | B9: Create a dashboard with KPI figures and at least 3 charts. | C9: Charts and storytelling

Sheet Dashboard
A1: SALES PERFORMANCE DASHBOARD
A3: Metric | B3: Value | D3: Product | E3: Quantity Sold | F3: Region | G3: Revenue | H3: Salesperson | I3: Total Profit
A4: Total Revenue | B4: =SUM('Raw Data'!$J$2:$J$121) | D4: Keyboard | E4: =SUMIF('Raw Data'!$C$2:$C$121,D4,'Raw Data'!$G$2:$G$121) | F4: Lagos | G4: =SUMIF('Raw Data'!$E$2:$E$121,F4,'Raw Data'!$J$2:$J$121) | H4: Aisha | I4: =SUMIF('Raw Data'!$F$2:$F$121,H4,'Raw Data'!$L$2:$L$121)
A5: Total Profit | B5: =SUM('Raw Data'!$L$2:$L$121) | D5: Headset | E5: =SUMIF('Raw Data'!$C$2:$C$121,D5,'Raw Data'!$G$2:$G$121) | F5: Abuja | G5: =SUMIF('Raw Data'!$E$2:$E$121,F5,'Raw Data'!$J$2:$J$121) | H5: David | I5: =SUMIF('Raw Data'!$F$2:$F$121,H5,'Raw Data'!$L$2:$L$121)
A6: Total Quantity | B6: =SUM('Raw Data'!$G$2:$G$121) | D6: Printer | E6: =SUMIF('Raw Data'!$C$2:$C$121,D6,'Raw Data'!$G$2:$G$121) | F6: Port Harcourt | G6: =SUMIF('Raw Data'!$E$2:$E$121,F6,'Raw Data'!$J$2:$J$121) | H6: Grace | I6: =SUMIF('Raw Data'!$F$2:$F$121,H6,'Raw Data'!$L$2:$L$121)
A7: Average Order Value | B7: =B4/COUNTA('Raw Data'!$A$2:$A$121) | D7: Monitor | E7: =SUMIF('Raw Data'!$C$2:$C$121,D7,'Raw Data'!$G$2:$G$121) | F7: Ibadan | G7: =SUMIF('Raw Data'!$E$2:$E$121,F7,'Raw Data'!$J$2:$J$121) | H7: Michael | I7: =SUMIF('Raw Data'!$F$2:$F$121,H7,'Raw Data'!$L$2:$L$121)
A8: Overall Profit Margin | B8: =B5/B4 | D8: Office Chair | E8: =SUMIF('Raw Data'!$C$2:$C$121,D8,'Raw Data'!$G$2:$G$121) | F8: Kano | G8: =SUMIF('Raw Data'!$E$2:$E$121,F8,'Raw Data'!$J$2:$J$121) | H8: Tunde | I8: =SUMIF('Raw Data'!$F$2:$F$121,H8,'Raw Data'!$L$2:$L$121)
D9: Laptop | E9: =SUMIF('Raw Data'!$C$2:$C$121,D9,'Raw Data'!$G$2:$G$121)
A10: KEY INSIGHTS
A11: Best-Selling Product: Keyboard — 145 units
A12: Highest-Revenue Region: Lagos — ₦39,725,775
A13: Top Salesperson by Profit: Grace — ₦6,298,335
